Metadata-Version: 2.1
Name: toml-dataclass
Version: 0.1.0
Summary: Interchangeable representation between toml and Python dataclass
Author-email: Daniel Martins Antunes <danoan2008@gmail.com>
License: MIT License
Project-URL: Documentation, https://github.com/danoan/toml-dataclass#readme
Project-URL: Issues, https://github.com/danoan/toml-dataclass/issues
Project-URL: Source, https://github.com/danoan/toml-dataclass
Classifier: Development Status :: 4 - Beta
Classifier: Programming Language :: Python
Classifier: Programming Language :: Python :: 3.8
Classifier: Programming Language :: Python :: 3.9
Classifier: Programming Language :: Python :: 3.10
Classifier: Programming Language :: Python :: Implementation :: CPython
Classifier: Programming Language :: Python :: Implementation :: PyPy
Requires-Python: >=3.8
License-File: LICENSE.txt
Requires-Dist: dataclasses
Requires-Dist: toml
Requires-Dist: typing_extensions
